eis_cream/__init__.py
eis_cream/eis_cream.py
eis_cream_cmd-0.0.1.dist-info/LICENSE
eis_cream_cmd-0.0.1.dist-info/METADATA
eis_cream_cmd-0.0.1.dist-info/WHEEL
eis_cream_cmd-0.0.1.dist-info/entry_points.txt
eis_cream_cmd-0.0.1.dist-info/top_level.txt
eis_cream_cmd-0.0.1.dist-info/RECORD
