Metadata-Version: 2.1
Name: eis_cream_cmd
Version: 0.0.1
Summary: data visualization tool for echem data
Home-page: https://github.com/yuefan98/Machine-Learning-on-EIS
Author: Emily Du
Author-email: emilydu@uw.edu
Project-URL: Bug Tracker, https://github.com/yuefan98/Machine-Learning-on-EIS
Classifier: Programming Language :: Python :: 3
Classifier: License :: OSI Approved :: MIT License
Classifier: Operating System :: OS Independent
Requires-Python: >=3.6
License-File: LICENSE
